README
setup.py
htmlfilter/__init__.py
htmlfilter/rules.py
htmlfilter.egg-info/PKG-INFO
htmlfilter.egg-info/SOURCES.txt
htmlfilter.egg-info/dependency_links.txt
htmlfilter.egg-info/top_level.txt
htmlfilter.egg-info/zip-safe