Metadata-Version: 1.0
Name: htmlfilter
Version: 0.2
Summary: White list HTML filter
Home-page: http://github.com/samueladam/htmlfilter
Author: Samuel Adam
Author-email: samuel.adam@gmail.com
License: BSD
Keywords: html,filter,white list,parser,clean,tags
Platform: UNKNOWN
Classifier: Development Status :: 4 - Beta
Classifier: Intended Audience :: Developers
Classifier: Topic :: Text Processing :: Filters
Classifier: Topic :: Text Processing :: Markup :: HTML
